calltrack/__init__.py
calltrack/calltrack.py
calltrack/cli.py
calltrack/dependencies.py
calltrack/log_queue.py
calltrack/setup.py
calltrack/utils.py
calltrack/view.py
calltrack-0.0.5.dist-info/METADATA
calltrack-0.0.5.dist-info/WHEEL
calltrack-0.0.5.dist-info/entry_points.txt
calltrack-0.0.5.dist-info/RECORD
