Metadata-Version: 2.1
Name: calltrack
Version: 0.0.5
Summary: 
Author: WILLIAM PONS
Author-email: wmpons.pro@gmail.com
Requires-Python: >=3.10,<4.0
Classifier: Programming Language :: Python :: 3
Classifier: Programming Language :: Python :: 3.10
Classifier: Programming Language :: Python :: 3.11
Classifier: Programming Language :: Python :: 3.12
Requires-Dist: pytest (>=8.2.0,<9.0.0)
Requires-Dist: pytest-mock (>=3.14.0,<4.0.0)
Requires-Dist: setuptools (>=69.5.1,<70.0.0)
Requires-Dist: streamlit (>=1.34.0,<2.0.0)
